st_pagination_buttons/__init__.py
st_pagination_buttons/example.py
st_pagination_buttons/frontend/build/asset-manifest.json
st_pagination_buttons/frontend/build/bootstrap.min.css
st_pagination_buttons/frontend/build/bootstrap.min.css.map
st_pagination_buttons/frontend/build/index.html
st_pagination_buttons/frontend/build/static/js/main.e4dc00c8.js
st_pagination_buttons/frontend/build/static/js/main.e4dc00c8.js.LICENSE.txt
st_pagination_buttons/frontend/build/static/js/main.e4dc00c8.js.map
st_pagination_buttons-0.2.0.dist-info/LICENSE
st_pagination_buttons-0.2.0.dist-info/METADATA
st_pagination_buttons-0.2.0.dist-info/WHEEL
st_pagination_buttons-0.2.0.dist-info/top_level.txt
st_pagination_buttons-0.2.0.dist-info/RECORD
