Metadata-Version: 2.1
Name: st-pagination-buttons
Version: 0.2.0
Summary: Streamlit pagination buttons component
Home-page: https://github.com/mysiar-org/st-pagination-buttons
Author: Piotr Synowiec
Author-email: psynowiec@gmail.com
License: MIT
Keywords: streamlit,streamlit-component
Requires-Python: >=3.7
License-File: LICENSE
Requires-Dist: streamlit >=0.63
Provides-Extra: devel
Requires-Dist: wheel ; extra == 'devel'
Requires-Dist: pytest ==7.4.0 ; extra == 'devel'
Requires-Dist: playwright ==1.39.0 ; extra == 'devel'
Requires-Dist: requests ==2.31.0 ; extra == 'devel'
Requires-Dist: pytest-playwright-snapshot ==1.0 ; extra == 'devel'
Requires-Dist: pytest-rerunfailures ==12.0 ; extra == 'devel'
